gcache/__init__.py
gcache/_internal/__init__.py
gcache/_internal/cache_interface.py
gcache/_internal/constants.py
gcache/_internal/event_loop_thread.py
gcache/_internal/local_cache.py
gcache/_internal/metrics.py
gcache/_internal/noop_cache.py
gcache/_internal/redis_cache.py
gcache/_internal/state.py
gcache/_internal/wrappers.py
gcache/config.py
gcache/exceptions.py
gcache/gcache.py
gcache-2.0.2.dist-info/METADATA
gcache-2.0.2.dist-info/WHEEL
gcache-2.0.2.dist-info/RECORD
