Metadata-Version: 2.3
Name: gcache
Version: 2.0.2
Summary: Fine grained caching.
License: MIT
Author: Galileo Technologies Inc.
Author-email: team@rungalileo.io
Requires-Python: >=3.10
Classifier: Development Status :: 5 - Production/Stable
Classifier: Intended Audience :: Developers
Classifier: Intended Audience :: Information Technology
Classifier: Intended Audience :: Science/Research
Classifier: Operating System :: OS Independent
Classifier: Programming Language :: Python :: 3 :: Only
Classifier: Programming Language :: Python :: 3.10
Classifier: Programming Language :: Python :: 3.11
Classifier: Programming Language :: Python :: 3.12
Classifier: Programming Language :: Python :: 3.13
Classifier: Programming Language :: Python :: 3.14
Classifier: Topic :: Software Development :: Libraries
Classifier: Topic :: Software Development :: Libraries :: Python Modules
Classifier: Typing :: Typed
Requires-Dist: cachetools (>=5.5.2)
Requires-Dist: prometheus-client (>=0.22.1,<0.23.0)
Requires-Dist: pydantic (>=2.11.4,<3.0.0)
Requires-Dist: redis (>=5.0.0)
Requires-Dist: types-cachetools (>=6.2.0.20250827,<7.0.0.0)
Requires-Dist: uvloop (>=0.21.0,<0.22.0)
Project-URL: Homepage, https://github.com/rungalileo/gcache
Project-URL: Repository, https://github.com/rungalileo/gcache
